odoo/addons/fieldservice_route_vehicle/README.rst
odoo/addons/fieldservice_route_vehicle/__init__.py
odoo/addons/fieldservice_route_vehicle/__manifest__.py
odoo/addons/fieldservice_route_vehicle/i18n/es.po
odoo/addons/fieldservice_route_vehicle/i18n/es_CL.po
odoo/addons/fieldservice_route_vehicle/i18n/fieldservice_route_vehicle.pot
odoo/addons/fieldservice_route_vehicle/models/__init__.py
odoo/addons/fieldservice_route_vehicle/models/fsm_order.py
odoo/addons/fieldservice_route_vehicle/models/fsm_route.py
odoo/addons/fieldservice_route_vehicle/models/fsm_route_dayroute.py
odoo/addons/fieldservice_route_vehicle/readme/CONFIGURE.rst
odoo/addons/fieldservice_route_vehicle/readme/CONTRIBUTORS.rst
odoo/addons/fieldservice_route_vehicle/readme/CREDITS.rst
odoo/addons/fieldservice_route_vehicle/readme/DESCRIPTION.rst
odoo/addons/fieldservice_route_vehicle/readme/ROADMAP.rst
odoo/addons/fieldservice_route_vehicle/readme/USAGE.rst
odoo/addons/fieldservice_route_vehicle/static/description/icon.png
odoo/addons/fieldservice_route_vehicle/static/description/index.html
odoo/addons/fieldservice_route_vehicle/views/fsm_route.xml
odoo/addons/fieldservice_route_vehicle/views/fsm_route_dayroute.xml
odoo12_addon_fieldservice_route_vehicle-12.0.2.1.1.dist-info/METADATA
odoo12_addon_fieldservice_route_vehicle-12.0.2.1.1.dist-info/WHEEL
odoo12_addon_fieldservice_route_vehicle-12.0.2.1.1.dist-info/top_level.txt
odoo12_addon_fieldservice_route_vehicle-12.0.2.1.1.dist-info/RECORD
