Metadata-Version: 2.1
Name: odoo12-addon-fieldservice-route-vehicle
Version: 12.0.2.1.1
Summary: This module allows you to set the vehicle on the routes and day routes.
Home-page: https://github.com/OCA/field-service
Author: Open Source Integrators, Odoo Community Association (OCA)
Author-email: support@odoo-community.org
License: AGPL-3
Platform: UNKNOWN
Classifier: Programming Language :: Python
Classifier: Framework :: Odoo
Classifier: License :: OSI Approved :: GNU Affero General Public License v3
Classifier: Development Status :: 4 - Beta
Requires-Python: >=3.5
Requires-Dist: odoo12-addon-fieldservice-route
Requires-Dist: odoo12-addon-fieldservice-vehicle-stock
Requires-Dist: odoo (<12.1dev,>=12.0a)
